{"title":"花王：旅行券や匂いケアグッズがもらえるキャンペーン実施　「今年の就活は“臭勝”！」","link":"http://mainichi.jp/bizbuz/news/20150531dog00m020002000c.html","datetimeInformation":"2015年06月01日","pages":"1","contents":["花王は、就職活動を行う学生に向けて、旅行券や匂いをケアするグッズなどを抽選でプレゼントするキャンペーン「今年の就活は“臭勝（しゅうかつ）”！」を実施している。7月31日まで。","同社は、今年から就職活動の面接解禁日が8月に後ろ倒しとなり、暑さの厳しい時期に就活が本格化することから、「今年の就活は、気になるニオイをケアする“臭勝”がポイント」と提案。プレゼントは3種類で、A賞の「JTB旅行券3万円分×2名様分」（3組6人）、B賞の「叙々苑 お食事券2万円分」（5人）、C賞の「携帯用リセッシュ除菌EX Plus　デオドラントパワー」（1000人）を用意する。","キャンペーン特設サイトでアンケートに答え、住所・氏名などを入力すると応募することができる。応募は1人1回まで。なお、特設サイトでは、花王社員によるスーツや靴、外出先での匂いケアのアドバイスをはじめ、衣料用消臭スプレー「リセッシュ」を活用した匂いケア術などを紹介している。"]}