{"title":"余録:旧制中学に通う主人公は勤労奉仕の毎日だ。時々…","link":"http://mainichi.jp/opinion/news/20150525k0000m070138000c.html","datetimeInformation":"毎日新聞　2015年05月25日　00時04分（最終更新　05月25日　00時04分）","pages":"1","contents":["旧制中学に通う主人公は勤労奉仕の毎日だ。時々、軍需工場の持ち場を離れ、隠れてペンをカリカリと紙に走らせる。好きな漫画を描くことは不謹慎ととがめられる時代。それでもペンを握った▲漫画家、手塚治虫の自伝的作品「紙の砦（とりで）」。敗戦の年、動員された大阪の工場は米軍の焼夷（しょうい）弾に焼き払われた。多くの仲間が死に、自分は生き残った。大阪と同じ７０年前、空襲で１０万人以上が犠牲になった東京。民間が運営する下町の「東京大空襲・戦災資料センター」には手塚の文章がパネルで紹介されている▲「ほとんどの作品のテーマには、この（大阪での）悪夢のような記憶を無意識に描いているものが多いのです。それはちょうど語り部のように自分の体験を子どもたちに語って聞かせたい。そういう気持ちが動いているのでしょう」▲センターには大空襲を生き延びた女性の語り部がいる。両親とはぐれ、炎の中を逃げ惑った。「赤ちゃんがお母さんにおぶわれたまま燃えていました」。思い出したくもないであろう８歳の記憶。それをなんとしても伝えようとする姿は手塚と重なる▲「悲しい歴史があったことを決して忘れてはならないと思う」。今年４月、天皇陛下は激戦地パラオの訪問でこう述べられた。陛下も小学校最後の年に敗戦を迎え、空襲の痛ましさを実感した少年だった。国内各地の慰霊の旅はこれからも続く▲手塚の「紙の砦」は昨年の大学入試センター試験に使われた。解くのは７０年前の主人公と同じ年ごろの若者たち。もし、こんな設問があったら、今を生きる彼らはどう答えるだろう。何を守ろうとする「砦」だと思いますか。"]}