{"title":"米国:対露外交に慎重姿勢要求　日本に「平常とは違う」","link":"http://mainichi.jp/select/news/20150522k0000e030219000c.html","datetimeInformation":"毎日新聞　2015年05月22日　11時37分","pages":"1","contents":["【ワシントン和田浩明】ラッセル米国務次官補（東アジア・太平洋担当）は２１日、ワシントンで外国記者らと会見し、日本の対ロシア外交について「我々（米国）はロシアに平常通りの対応はしていない。日本政府も現状ではこの原則を守ってくれると思う」と述べ、日露政府高官の相互訪問などに慎重な対応を求めた。","国務省のハーフ副報道官は２０日の定例会見で、安倍晋三首相が日露関係の改善に向けプーチン露大統領の訪日を求める意向を示したことについて「反対する理由はない」と述べていたが、ラッセル氏はこれを修正した形だ。","米国はウクライナ危機後初めてケリー国務長官がロシアを訪れ、１２日にプーチン氏らと会談。その後も国務省幹部が相次いで訪露し、ウクライナ問題やシリア内戦への対応について協議していた。","ラッセル氏はケリー氏の訪露について、ウクライナでの停戦合意の履行をロシアに促す「緊急で特定の目的」によるもので、「平常通りの対応とは大きく違う」と説明。事前に日本政府にも説明を行っており「（日本側に）誤解はないと期待している」と述べた。"]}